{
  "dataset": "blog_data",
  "seed": 17,
  "model": "Ridge",
  "split": [
    0.5,
    0.25,
    0.25
  ],
  "alphas": [
    0.01,
    0.02,
    0.05,
    0.1
  ],
  "result": {
    "seed": 17,
    "model": "Ridge",
    "model_rmse": 0.7125525493898769,
    "meta": {
      "n_train": 26198,
      "n_cal": 13099,
      "n_test": 13100,
      "d": 4,
      "p": 277,
      "elapsed": 31328.301424264908
    },
    "Mahal": {
      "params": {},
      "0.01": {
        "coverage": 0.9889312977099237,
        "volume": 1212.490961918349,
        "wsc": 0.9595419847328245,
        "threshold": 36.47125825872424
      },
      "0.02": {
        "coverage": 0.9802290076335878,
        "volume": 289.18281166655106,
        "wsc": 0.9312977099236641,
        "threshold": 17.811386580252265
      },
      "0.05": {
        "coverage": 0.953206106870229,
        "volume": 42.5616213490853,
        "wsc": 0.8564885496183207,
        "threshold": 6.83314400860335
      },
      "0.1": {
        "coverage": 0.9032824427480916,
        "volume": 15.800766675719498,
        "wsc": 0.7687022900763358,
        "threshold": 4.163423332769332
      }
    },
    "Bonferroni": {
      "params": {},
      "0.01": {
        "coverage": 0.9893129770992366,
        "volume": 3238.0947648185224,
        "wsc": 0.9606870229007634,
        "threshold": 5.932343560305914
      },
      "0.02": {
        "coverage": 0.98,
        "volume": 730.3141719019059,
        "wsc": 0.9301526717557251,
        "threshold": 3.972232770070614
      },
      "0.05": {
        "coverage": 0.952824427480916,
        "volume": 80.29128815511407,
        "wsc": 0.8583969465648855,
        "threshold": 2.3373423835515186
      },
      "0.1": {
        "coverage": 0.9057251908396946,
        "volume": 37.50132021616106,
        "wsc": 0.7816793893129771,
        "threshold": 1.8646970796498223
      }
    },
    "Density": {
      "params": {
        "lengthscale": 2.4278358353057232
      },
      "0.01": {
        "coverage": 0.9901526717557252,
        "volume": 1607.2681215721339,
        "wsc": 0.9629770992366412,
        "threshold": 1.4010496696006798
      },
      "0.02": {
        "coverage": 0.980763358778626,
        "volume": 414.9184531608589,
        "wsc": 0.9278625954198473,
        "threshold": 0.9676221382915976
      },
      "0.05": {
        "coverage": 0.9511450381679389,
        "volume": 63.94455883012079,
        "wsc": 0.8652671755725191,
        "threshold": 0.47906907087832473
      },
      "0.1": {
        "coverage": 0.9032824427480916,
        "volume": 32.69345864998657,
        "wsc": 0.7847328244274809,
        "threshold": 0.35393018851246294
      }
    },
    "Kernel": {
      "params": {
        "lengthscale": 2.4278358353057232,
        "gamma": 0.999998125214521
      },
      "0.01": {
        "coverage": 0.9883206106870229,
        "volume": 165.39043787640264,
        "wsc": 0.9561068702290076,
        "threshold": 0.05861474305513749
      },
      "0.02": {
        "coverage": 0.9809160305343512,
        "volume": 74.52185427570468,
        "wsc": 0.933969465648855,
        "threshold": 0.02853581969893972
      },
      "0.05": {
        "coverage": 0.9514503816793893,
        "volume": 16.346729324993284,
        "wsc": 0.850763358778626,
        "threshold": 0.0072019452827460275
      },
      "0.1": {
        "coverage": 0.9035114503816793,
        "volume": 4.807861566174495,
        "wsc": 0.7480916030534351,
        "threshold": 0.002889608369088532
      }
    }
  },
  "elapsed_s": 31328.30465221405
}